metalq/__init__.py
metalq/api.py
metalq/circuit.py
metalq/parameter.py
metalq/result.py
metalq/spin.py
metalq/visualization.py
metalq/lib/libmetalq.dylib
metalq/lib/quantum_gates.metallib
metalq/python/metalq/lib/libmetalq.dylib
metalq/python/metalq/lib/quantum_gates.metallib
metalq-1.0.0.dist-info/licenses/LICENSE
metalq-1.0.0.dist-info/METADATA
metalq-1.0.0.dist-info/WHEEL
metalq-1.0.0.dist-info/top_level.txt
metalq-1.0.0.dist-info/RECORD
