Metadata-Version: 2.4
Name: metalq
Version: 1.0.0
Summary: High-performance quantum circuit simulator for Apple Silicon using Metal GPU
Author: Metal-Q Contributors
License: MIT
Project-URL: Homepage, https://github.com/masa-whitestone/metal-quantum
Project-URL: Repository, https://github.com/masa-whitestone/metal-quantum.git
Project-URL: Issues, https://github.com/masa-whitestone/metal-quantum/issues
Keywords: quantum,quantum-computing,simulator,qiskit,apple-silicon,metal,gpu
Classifier: Development Status :: 4 - Beta
Classifier: Intended Audience :: Science/Research
Classifier: Intended Audience :: Developers
Classifier: License :: OSI Approved :: MIT License
Classifier: Operating System :: MacOS :: MacOS X
Classifier: Programming Language :: Python :: 3
Classifier: Programming Language :: Python :: 3.10
Classifier: Programming Language :: Python :: 3.11
Classifier: Programming Language :: Python :: 3.12
Classifier: Topic :: Scientific/Engineering :: Physics
Requires-Python: >=3.10
License-File: LICENSE
Requires-Dist: numpy>=1.21.0
Requires-Dist: qiskit>=2.2.3
Requires-Dist: torch>=2.9.1
Provides-Extra: dev
Requires-Dist: pytest>=7.0.0; extra == "dev"
Provides-Extra: performance
Requires-Dist: numba>=0.56.0; extra == "performance"
Requires-Dist: polars>=0.17.0; extra == "performance"
Dynamic: license-file
